{
  "annotations": {
    "list": []
  },
  "editable": true,
  "gnetId": null,
  "graphTooltip": 0,
  "id": null,
  "links": [],
  "panels": [
    {
      "datasource": "Prometheus",
      "fieldConfig": {
        "defaults": {
          "mappings": [],
          "thresholds": {
            "mode": "absolute",
            "steps": [
              {
                "color": "green",
                "value": null
              },
              {
                "color": "red",
                "value": 0
              }
            ]
          },
          "unit": "none"
        }
      },
      "gridPos": {
        "h": 4,
        "w": 6,
        "x": 0,
        "y": 0
      },
      "id": 1,
      "options": {
        "colorMode": "value",
        "graphMode": "area",
        "justifyMode": "auto",
        "orientation": "auto",
        "reduceOptions": {
          "calcs": ["lastNotNull"],
          "fields": "",
          "values": false
        },
        "text": {},
        "textMode": "auto"
      },
      "pluginVersion": "9.0.0",
      "targets": [
        {
          "expr": "up{service=\"user-service\"}",
          "refId": "A"
        }
      ],
      "title": "User Service",
      "type": "stat"
    },
    {
      "datasource": "Prometheus",
      "fieldConfig": {
        "defaults": {
          "mappings": [],
          "thresholds": {
            "mode": "absolute",
            "steps": [
              {
                "color": "green",
                "value": null
              },
              {
                "color": "red",
                "value": 0
              }
            ]
          },
          "unit": "none"
        }
      },
      "gridPos": {
        "h": 4,
        "w": 6,
        "x": 6,
        "y": 0
      },
      "id": 2,
      "options": {
        "colorMode": "value",
        "graphMode": "area",
        "justifyMode": "auto",
        "orientation": "auto",
        "reduceOptions": {
          "calcs": ["lastNotNull"],
          "fields": "",
          "values": false
        },
        "text": {},
        "textMode": "auto"
      },
      "pluginVersion": "9.0.0",
      "targets": [
        {
          "expr": "up{service=\"video-service\"}",
          "refId": "A"
        }
      ],
      "title": "Video Service",
      "type": "stat"
    },
    {
      "datasource": "Prometheus",
      "fieldConfig": {
        "defaults": {
          "mappings": [],
          "thresholds": {
            "mode": "absolute",
            "steps": [
              {
                "color": "green",
                "value": null
              },
              {
                "color": "red",
                "value": 0
              }
            ]
          },
          "unit": "none"
        }
      },
      "gridPos": {
        "h": 4,
        "w": 6,
        "x": 12,
        "y": 0
      },
      "id": 3,
      "options": {
        "colorMode": "value",
        "graphMode": "area",
        "justifyMode": "auto",
        "orientation": "auto",
        "reduceOptions": {
          "calcs": ["lastNotNull"],
          "fields": "",
          "values": false
        },
        "text": {},
        "textMode": "auto"
      },
      "pluginVersion": "9.0.0",
      "targets": [
        {
          "expr": "up{service=\"job-service\"}",
          "refId": "A"
        }
      ],
      "title": "Job Service",
      "type": "stat"
    },
    {
      "datasource": "Prometheus",
      "fieldConfig": {
        "defaults": {
          "mappings": [],
          "thresholds": {
            "mode": "absolute",
            "steps": [
              {
                "color": "green",
                "value": null
              },
              {
                "color": "red",
                "value": 0
              }
            ]
          },
          "unit": "none"
        }
      },
      "gridPos": {
        "h": 4,
        "w": 6,
        "x": 18,
        "y": 0
      },
      "id": 4,
      "options": {
        "colorMode": "value",
        "graphMode": "area",
        "justifyMode": "auto",
        "orientation": "auto",
        "reduceOptions": {
          "calcs": ["lastNotNull"],
          "fields": "",
          "values": false
        },
        "text": {},
        "textMode": "auto"
      },
      "pluginVersion": "9.0.0",
      "targets": [
        {
          "expr": "up{service=\"api-gateway\"}",
          "refId": "A"
        }
      ],
      "title": "API Gateway",
      "type": "stat"
    },
    {
      "datasource": "Prometheus",
      "fieldConfig": {
        "defaults": {
          "color": {
            "mode": "palette-classic"
          },
          "custom": {
            "axisLabel": "",
            "axisPlacement": "auto",
            "barAlignment": 0,
            "drawStyle": "line",
            "fillOpacity": 10,
            "gradientMode": "none",
            "hideFrom": {
              "tooltip": false,
              "viz": false,
              "legend": false
            },
            "lineInterpolation": "linear",
            "lineWidth": 1,
            "pointSize": 5,
            "scaleDistribution": {
              "type": "linear"
            },
            "showPoints": "never",
            "spanNulls": true,
            "stacking": {
              "group": "A",
              "mode": "none"
            },
            "thresholdsStyle": {
              "mode": "off"
            }
          },
          "mappings": [],
          "thresholds": {
            "mode": "absolute",
            "steps": [
              {
                "color": "green",
                "value": null
              }
            ]
          },
          "unit": "reqps"
        }
      },
      "gridPos": {
        "h": 8,
        "w": 12,
        "x": 0,
        "y": 4
      },
      "id": 5,
      "options": {
        "legend": {
          "calcs": ["mean", "max"],
          "displayMode": "table",
          "placement": "bottom"
        },
        "tooltip": {
          "mode": "multi"
        }
      },
      "pluginVersion": "9.0.0",
      "targets": [
        {
          "expr": "rate(http_requests_total[1m])",
          "legendFormat": "{{service}} - {{method}} {{path}}",
          "refId": "A"
        }
      ],
      "title": "Request Rate (per second)",
      "type": "timeseries"
    },
    {
      "datasource": "Prometheus",
      "fieldConfig": {
        "defaults": {
          "color": {
            "mode": "palette-classic"
          },
          "custom": {
            "axisLabel": "",
            "axisPlacement": "auto",
            "barAlignment": 0,
            "drawStyle": "line",
            "fillOpacity": 10,
            "gradientMode": "none",
            "hideFrom": {
              "tooltip": false,
              "viz": false,
              "legend": false
            },
            "lineInterpolation": "linear",
            "lineWidth": 1,
            "pointSize": 5,
            "scaleDistribution": {
              "type": "linear"
            },
            "showPoints": "never",
            "spanNulls": true,
            "stacking": {
              "group": "A",
              "mode": "none"
            },
            "thresholdsStyle": {
              "mode": "off"
            }
          },
          "mappings": [],
          "thresholds": {
            "mode": "absolute",
            "steps": [
              {
                "color": "green",
                "value": null
              },
              {
                "color": "yellow",
                "value": 0.5
              },
              {
                "color": "red",
                "value": 1
              }
            ]
          },
          "unit": "s"
        }
      },
      "gridPos": {
        "h": 8,
        "w": 12,
        "x": 12,
        "y": 4
      },
      "id": 6,
      "options": {
        "legend": {
          "calcs": ["mean", "max"],
          "displayMode": "table",
          "placement": "bottom"
        },
        "tooltip": {
          "mode": "multi"
        }
      },
      "pluginVersion": "9.0.0",
      "targets": [
        {
          "expr": "histogram_quantile(0.95, rate(http_request_duration_seconds_bucket[5m]))",
          "legendFormat": "{{service}} - p95",
          "refId": "A"
        },
        {
          "expr": "histogram_quantile(0.50, rate(http_request_duration_seconds_bucket[5m]))",
          "legendFormat": "{{service}} - p50",
          "refId": "B"
        }
      ],
      "title": "Response Time (p50, p95)",
      "type": "timeseries"
    },
    {
      "datasource": "Prometheus",
      "fieldConfig": {
        "defaults": {
          "color": {
            "mode": "palette-classic"
          },
          "custom": {
            "axisLabel": "",
            "axisPlacement": "auto",
            "barAlignment": 0,
            "drawStyle": "line",
            "fillOpacity": 10,
            "gradientMode": "none",
            "hideFrom": {
              "tooltip": false,
              "viz": false,
              "legend": false
            },
            "lineInterpolation": "linear",
            "lineWidth": 1,
            "pointSize": 5,
            "scaleDistribution": {
              "type": "linear"
            },
            "showPoints": "never",
            "spanNulls": true,
            "stacking": {
              "group": "A",
              "mode": "none"
            },
            "thresholdsStyle": {
              "mode": "off"
            }
          },
          "mappings": [],
          "thresholds": {
            "mode": "absolute",
            "steps": [
              {
                "color": "green",
                "value": null
              }
            ]
          },
          "unit": "percentunit"
        }
      },
      "gridPos": {
        "h": 8,
        "w": 12,
        "x": 0,
        "y": 12
      },
      "id": 7,
      "options": {
        "legend": {
          "calcs": ["mean", "max"],
          "displayMode": "table",
          "placement": "bottom"
        },
        "tooltip": {
          "mode": "multi"
        }
      },
      "pluginVersion": "9.0.0",
      "targets": [
        {
          "expr": "rate(http_requests_total{status=~\"5..\"}[5m]) / rate(http_requests_total[5m])",
          "legendFormat": "{{service}} - Error Rate",
          "refId": "A"
        }
      ],
      "title": "Error Rate (5xx)",
      "type": "timeseries"
    },
    {
      "datasource": "Prometheus",
      "fieldConfig": {
        "defaults": {
          "color": {
            "mode": "palette-classic"
          },
          "custom": {
            "axisLabel": "",
            "axisPlacement": "auto",
            "barAlignment": 0,
            "drawStyle": "line",
            "fillOpacity": 10,
            "gradientMode": "none",
            "hideFrom": {
              "tooltip": false,
              "viz": false,
              "legend": false
            },
            "lineInterpolation": "linear",
            "lineWidth": 1,
            "pointSize": 5,
            "scaleDistribution": {
              "type": "linear"
            },
            "showPoints": "never",
            "spanNulls": true,
            "stacking": {
              "group": "A",
              "mode": "none"
            },
            "thresholdsStyle": {
              "mode": "off"
            }
          },
          "mappings": [],
          "thresholds": {
            "mode": "absolute",
            "steps": [
              {
                "color": "green",
                "value": null
              }
            ]
          },
          "unit": "none"
        }
      },
      "gridPos": {
        "h": 8,
        "w": 12,
        "x": 12,
        "y": 12
      },
      "id": 8,
      "options": {
        "legend": {
          "calcs": ["last"],
          "displayMode": "table",
          "placement": "bottom"
        },
        "tooltip": {
          "mode": "multi"
        }
      },
      "pluginVersion": "9.0.0",
      "targets": [
        {
          "expr": "bull_queue_waiting",
          "legendFormat": "Waiting",
          "refId": "A"
        },
        {
          "expr": "bull_queue_active",
          "legendFormat": "Active",
          "refId": "B"
        },
        {
          "expr": "bull_queue_completed",
          "legendFormat": "Completed",
          "refId": "C"
        },
        {
          "expr": "bull_queue_failed",
          "legendFormat": "Failed",
          "refId": "D"
        }
      ],
      "title": "Bull Queue Status",
      "type": "timeseries"
    }
  ],
  "schemaVersion": 36,
  "style": "dark",
  "tags": ["microservices", "overview"],
  "templating": {
    "list": []
  },
  "time": {
    "from": "now-1h",
    "to": "now"
  },
  "timepicker": {},
  "timezone": "",
  "title": "Microservices Overview",
  "uid": "microservices-overview",
  "version": 1
}
